e2e_client/__init__.py
e2e_client/constants.py
e2e_client/domain.py
e2e_client/exceptions.py
e2e_client/manager.py
e2e_client/request_service.py
e2e_client-1.3.0.dist-info/METADATA
e2e_client-1.3.0.dist-info/WHEEL
e2e_client-1.3.0.dist-info/top_level.txt
e2e_client-1.3.0.dist-info/RECORD
