Metadata-Version: 2.1
Name: e2e-client
Version: 1.3.0
Summary: This a E2E Client tool for Certbot Plugin
Home-page: UNKNOWN
Author: Abhay Bhati
Author-email: abhaybhati987@gmail.com
License: UNKNOWN
Platform: UNKNOWN
Requires-Dist: requests
Requires-Dist: setuptools
Requires-Dist: python-whois
